{
    "dbConfig": {
        "adapter": "mongodb",
        "mongoDb": {
            "host": "mongodb://localhost:27017/admin?readPreference=primary&appname=MongoDB%20Compass%20Community&ssl=false",
            "options": {
                "useNewUrlParser": true,
                "useUnifiedTopology": true,
                "useFindAndModify": false
            }
        },
        "redis": {
            "server": "localhost",
            "port": 6379,
            "username": "admin",
            "password": "qgs@123"
        },
        "mysql": {
            "host": "localhost",
            "database": "qupworldLab",
            "user": "root",
            "password": "root"
        },
        "redisMapProvider": {
            "server": "localhost",
            "port": 6379,
            "index": 0,
            "username": "admin",
            "password": "qgs@123"
        }
    }
}